odoo/addons/product_packaging_calculator_packaging_level/README.rst
odoo/addons/product_packaging_calculator_packaging_level/__init__.py
odoo/addons/product_packaging_calculator_packaging_level/__manifest__.py
odoo/addons/product_packaging_calculator_packaging_level/i18n/it.po
odoo/addons/product_packaging_calculator_packaging_level/i18n/product_packaging_calculator_packaging_level.pot
odoo/addons/product_packaging_calculator_packaging_level/i18n/stock_packaging_calculator_packaging_level.pot
odoo/addons/product_packaging_calculator_packaging_level/i18n/stock_packaging_calculator_packaging_type.pot
odoo/addons/product_packaging_calculator_packaging_level/models/__init__.py
odoo/addons/product_packaging_calculator_packaging_level/models/product.py
odoo/addons/product_packaging_calculator_packaging_level/models/product_qty_by_packaging_mixin.py
odoo/addons/product_packaging_calculator_packaging_level/readme/CONTRIBUTORS.md
odoo/addons/product_packaging_calculator_packaging_level/readme/CREDITS.md
odoo/addons/product_packaging_calculator_packaging_level/readme/DESCRIPTION.md
odoo/addons/product_packaging_calculator_packaging_level/static/description/icon.png
odoo/addons/product_packaging_calculator_packaging_level/static/description/index.html
odoo/addons/product_packaging_calculator_packaging_level/tests/__init__.py
odoo/addons/product_packaging_calculator_packaging_level/tests/test_packaging_by_qty.py
odoo_addon_product_packaging_calculator_packaging_level-18.0.1.0.0.2.dist-info/METADATA
odoo_addon_product_packaging_calculator_packaging_level-18.0.1.0.0.2.dist-info/WHEEL
odoo_addon_product_packaging_calculator_packaging_level-18.0.1.0.0.2.dist-info/top_level.txt
odoo_addon_product_packaging_calculator_packaging_level-18.0.1.0.0.2.dist-info/RECORD
